llm_mistral.py
llm_mistral-0.15.dist-info/licenses/LICENSE
llm_mistral-0.15.dist-info/METADATA
llm_mistral-0.15.dist-info/WHEEL
llm_mistral-0.15.dist-info/entry_points.txt
llm_mistral-0.15.dist-info/top_level.txt
llm_mistral-0.15.dist-info/RECORD
