Metadata-Version: 2.4
Name: llm-mistral
Version: 0.15
Summary: LLM plugin providing access to Mistral models using the Mistral API
Author: Simon Willison
License: Apache-2.0
Project-URL: Homepage, https://github.com/simonw/llm-mistral
Project-URL: Changelog, https://github.com/simonw/llm-mistral/releases
Project-URL: Issues, https://github.com/simonw/llm-mistral/issues
Project-URL: CI, https://github.com/simonw/llm-mistral/actions
Classifier: License :: OSI Approved :: Apache Software License
License-File: LICENSE
Requires-Dist: llm>=0.26
Requires-Dist: httpx
Requires-Dist: httpx-sse
Provides-Extra: test
Requires-Dist: cogapp; extra == "test"
Requires-Dist: pytest; extra == "test"
Requires-Dist: pytest-httpx; extra == "test"
Requires-Dist: pytest-asyncio; extra == "test"
Dynamic: license-file
